LICENSE
README.md
setup.py
jscx/__init__.py
jscx/jsrun.py
jscx.egg-info/PKG-INFO
jscx.egg-info/SOURCES.txt
jscx.egg-info/dependency_links.txt
jscx.egg-info/top_level.txt